readee/__init__.py
readee/article.py
readee/common.py
readee/content.py
readee/domain.py
readee/final_touch.py
readee/images.py
readee/inner_article.py
readee/link.py
readee/offtopic.py
readee/tag_replace.py
readee-0.0.136.dist-info/LICENSE
readee-0.0.136.dist-info/METADATA
readee-0.0.136.dist-info/WHEEL
readee-0.0.136.dist-info/top_level.txt
readee-0.0.136.dist-info/RECORD
