Metadata-Version: 2.1
Name: readee
Version: 0.0.136
Summary: Library for export webpage to reader mode html.
Home-page: https://github.com/gaoyunzhi/readee
Author: Yunzhi Gao
Author-email: gaoyunzhi@gmail.com
License: UNKNOWN
Platform: UNKNOWN
Classifier: Programming Language :: Python :: 3
Classifier: License :: OSI Approved :: MIT License
Classifier: Operating System :: OS Independent
Requires-Python: >=3.0
License-File: LICENSE
Requires-Dist: bs4
Requires-Dist: readability-lxml
Requires-Dist: telegram-util
Requires-Dist: opencc-python-reimplemented
Requires-Dist: cached-url
